b2_cleanup/__init__.py
b2_cleanup/cli.py
b2_cleanup/core.py
b2_cleanup-0.1.4.dist-info/METADATA
b2_cleanup-0.1.4.dist-info/WHEEL
b2_cleanup-0.1.4.dist-info/entry_points.txt
b2_cleanup-0.1.4.dist-info/RECORD
