Metadata-Version: 2.4
Name: b2-cleanup
Version: 0.1.4
Summary: CLI tool to clean up unfinished Backblaze B2 large uploads
Project-URL: Homepage, https://github.com/your-username/b2-cleanup
Project-URL: Issues, https://github.com/your-username/b2-cleanup/issues
Project-URL: Changelog, https://github.com/your-username/b2-cleanup/blob/main/CHANGELOG.md
Author-email: Jeroen Verhoeven <jeroen@joentje.org>
License: MIT
Keywords: b2,backblaze,cleanup,cli,cloud-storage
Classifier: Development Status :: 4 - Beta
Classifier: Intended Audience :: Developers
Classifier: License :: OSI Approved :: MIT License
Classifier: Programming Language :: Python :: 3
Classifier: Programming Language :: Python :: 3.8
Classifier: Programming Language :: Python :: 3.9
Classifier: Programming Language :: Python :: 3.10
Classifier: Programming Language :: Python :: 3.11
Classifier: Topic :: Utilities
Requires-Python: >=3.8
Requires-Dist: b2sdk>=1.20.0
Requires-Dist: click>=8.0
Provides-Extra: dev
Requires-Dist: pytest-cov>=4.0.0; extra == 'dev'
Requires-Dist: pytest-mock>=3.10.0; extra == 'dev'
Requires-Dist: pytest>=7.0.0; extra == 'dev'
